disseqt_agentic_sdk/__init__.py
disseqt_agentic_sdk/api/__init__.py
disseqt_agentic_sdk/api/client.py
disseqt_agentic_sdk/api/helpers.py
disseqt_agentic_sdk/api/trace.py
disseqt_agentic_sdk/buffer/__init__.py
disseqt_agentic_sdk/buffer/buffer.py
disseqt_agentic_sdk/client/__init__.py
disseqt_agentic_sdk/client/client.py
disseqt_agentic_sdk/context/__init__.py
disseqt_agentic_sdk/context/context.py
disseqt_agentic_sdk/enums/__init__.py
disseqt_agentic_sdk/enums/span_kind.py
disseqt_agentic_sdk/enums/status.py
disseqt_agentic_sdk/models/__init__.py
disseqt_agentic_sdk/models/span.py
disseqt_agentic_sdk/semantics/__init__.py
disseqt_agentic_sdk/semantics/agentic.py
disseqt_agentic_sdk/span/__init__.py
disseqt_agentic_sdk/span/span.py
disseqt_agentic_sdk/trace/__init__.py
disseqt_agentic_sdk/trace/trace.py
disseqt_agentic_sdk/transport/__init__.py
disseqt_agentic_sdk/transport/http.py
disseqt_agentic_sdk/utils/__init__.py
disseqt_agentic_sdk/utils/ids.py
disseqt_agentic_sdk/utils/logging.py
disseqt_agentic_sdk/utils/time.py
disseqt_sdk/__init__.py
disseqt_sdk/client.py
disseqt_sdk/enums.py
disseqt_sdk/registry.py
disseqt_sdk/response.py
disseqt_sdk/routes.py
disseqt_sdk/models/__init__.py
disseqt_sdk/models/agentic_behaviour.py
disseqt_sdk/models/base.py
disseqt_sdk/models/composite_score.py
disseqt_sdk/models/input_validation.py
disseqt_sdk/models/mcp_security.py
disseqt_sdk/models/output_validation.py
disseqt_sdk/models/rag_grounding.py
disseqt_sdk/models/themes_classifier.py
disseqt_sdk/validators/__init__.py
disseqt_sdk/validators/base.py
disseqt_sdk/validators/agentic_behavior/__init__.py
disseqt_sdk/validators/agentic_behavior/agent_goal_accuracy.py
disseqt_sdk/validators/agentic_behavior/fallback_rate.py
disseqt_sdk/validators/agentic_behavior/intent_resolution.py
disseqt_sdk/validators/agentic_behavior/plan_coherence.py
disseqt_sdk/validators/agentic_behavior/plan_optimality.py
disseqt_sdk/validators/agentic_behavior/reliability.py
disseqt_ai_sdk-0.2.5.dist-info/METADATA
disseqt_ai_sdk-0.2.5.dist-info/WHEEL
disseqt_ai_sdk-0.2.5.dist-info/licenses/LICENSE
disseqt_ai_sdk-0.2.5.dist-info/RECORD
