Metadata-Version: 2.4
Name: disseqt-ai-sdk
Version: 0.2.5
Summary: Python SDK for disseqt.ai
Project-URL: Homepage, https://disseqt.ai
Project-URL: Documentation, https://github.com/DisseqtAI/disseqt-python-sdk#readme
Project-URL: Repository, https://github.com/DisseqtAI/disseqt-python-sdk
Project-URL: Issues, https://github.com/DisseqtAI/disseqt-python-sdk/issues
Project-URL: Changelog, https://github.com/DisseqtAI/disseqt-python-sdk/blob/main/CHANGELOG.md
Author-email: Disseqt AI Limited <support@disseqt.ai>
License: Proprietary
License-File: LICENSE
Keywords: agentic,ai,genai,guardrails,llm,machine-learning,monitoring,observability,opentelemetry,otel,safety,sdk,telemetry,tracing,validation
Classifier: Development Status :: 3 - Alpha
Classifier: Intended Audience :: Developers
Classifier: License :: Other/Proprietary License
Classifier: Programming Language :: Python :: 3
Classifier: Programming Language :: Python :: 3.10
Classifier: Programming Language :: Python :: 3.11
Classifier: Programming Language :: Python :: 3.12
Classifier: Topic :: Software Development :: Libraries :: Python Modules
Requires-Python: >=3.10.14
Requires-Dist: requests>=2.31.0
Requires-Dist: typing-extensions>=4.8.0
